<?xml version="1.0" encoding="UTF-8"?>
<ROM>
  <RomName>Cosmic-OS_land_8.1.0</RomName>
  <VersionName><![CDATA[ Cosmic-OS_Universe_land_8.1.0_20180130_3.1-OFFICIAL ]]></VersionName>
  <VersionNumber type="integer">20180130</VersionNumber>
  <DirectUrl>https://downloads.sourceforge.net/project/cosmic-os/land/Cosmic-OS_Universe_land_8.1.0_20180130_3.1-OFFICIAL.zip</DirectUrl>
  <HttpUrl>https://sourceforge.net/projects/cosmic-os/files/land</HttpUrl>
  <Android>8.1.0</Android>
  <CheckMD5>7ecb1a552612009645d606ab138f7fe7</CheckMD5>
  <FileSize type="integer">503747921</FileSize>
  <Developer>klozz(TeamMEX)</Developer>
  <WebsiteURL nil="true">cosmic-os.github.io</WebsiteURL>
  <DonateURL nil="true"/>paypal.me/Cosmic-OS</DonateURL>
  <Changelog>====================
     01-30-2018
====================

   * bionic/
a8d166a  Squashed revert of FUTEX_WAIT_BITSET related patches  [klozz]

   * device/*/land
     Fixed camera issues
		 Fixed Ril issues
</Changelog>
</ROM>
